hikac/__init__.py
hikac/src/__init__.py
hikac/src/hikac.py
hikac/test/__init__.py
hikac/test/test_hikac.py
hikac-0.0.15.dist-info/LICENSE
hikac-0.0.15.dist-info/METADATA
hikac-0.0.15.dist-info/WHEEL
hikac-0.0.15.dist-info/top_level.txt
hikac-0.0.15.dist-info/RECORD
