Metadata-Version: 2.1
Name: hikac
Version: 0.0.15
Summary: A hikvision access control request manager
Home-page: https://github.com/yusufjonc07/hikac
Author: YusufAxmad
Author-email: studentyusufaxmad@gmail.com
License: MIT
Platform: UNKNOWN
Classifier: License :: OSI Approved :: MIT License
Classifier: Programming Language :: Python :: 3.8
Classifier: Operating System :: OS Independent
Requires-Python: >=3.8
License-File: LICENSE
Requires-Dist: starlette
Provides-Extra: dev
Requires-Dist: pytest >=7.0 ; extra == 'dev'
Requires-Dist: twine >=4.0.2 ; extra == 'dev'
